[
    { 
        "username" : "Molly48", 
        "email" : "Molly48_Waters59@hotmail.com", 
        "password" : "kGjRfUNWUIRwfS_", 
        "friends" : [], 
        "thoughts" : [],
        "stats": {"currentCh": 10}
    },
    { 
        "username" : "Katlyn85", 
        "email" : "Katlyn8550@gmail.com", 
        "password" : "otK5YtXpcalD1cm", 
        "friends" : [], 
        "thoughts" : [] ,
        "stats": {"currentCh": 0}
    },
    { 
        "username" : "Lessie_Kautzer61", 
        "email" : "Lessie_Kautzer61_Walker81@hotmail.com", 
        "password" : "AP3EUTRZoxzsiHn", 
        "friends" : [], 
        "thoughts" : [] ,
        "stats": {"currentCh": 0}
    },
    { 
        "username" : "Elton_Heaney", 
        "email" : "Elton_Heaney.Kemmer6@yahoo.com", 
        "password" : "3dVgRgSQmrGLaQE", 
        "friends" : [], 
        "thoughts" : [] ,
        "stats": {"currentCh": 0}
    },
    { 
        "username" : "Josue67", 
        "email" : "Josue6785@yahoo.com", 
        "password" : "BNsmR75BHDH4na3", 
        "friends" : [], 
        "thoughts" : [] ,
        "stats": {"currentCh": 0}
    },
    { 
        "username" : "Jaron98", 
        "email" : "Jaron98_Will72@hotmail.com", 
        "password" : "vNVT_y10PBpVaUV", 
        "friends" : [], 
        "thoughts" : [] ,
        "stats": {"currentCh": 0}
    },
    { 
        "username" : "Colt.Windler", 
        "email" : "Colt.Windler_Corwin@hotmail.com", 
        "password" : "bBDsrGqpDHI1YTa", 
        "thoughts" : [] ,
        "stats": {"currentCh": 0}
    },
    { 
        "username" : "Berta.Schmeler15", 
        "email" : "Berta.Schmeler15_Hackett93@hotmail.com", 
        "password" : "_cbdQwR8Vjn4wBk", 
        "friends" : [], 
        "thoughts" : [] ,
        "stats": {"currentCh": 0}
    },
    { 
        "username" : "Kaley35", 
        "email" : "Kaley35_Carroll@yahoo.com", 
        "password" : "OodrBk3d1t5Ddhb", 
        "friends" : [], 
        "thoughts" : [] ,
        "stats": {"currentCh": 0}
    },
    { 
        "username" : "Bryana.Hackett", 
        "email" : "Bryana.Hackett94@yahoo.com", 
        "password" : "WZ3brF0TKThmwU8", 
        "friends" : [], 
        "thoughts" : [] ,
        "stats": {"currentCh": 0}
    },
    { 
        "username" : "Madge.Feil", 
        "email" : "Madge.Feil_Fadel@yahoo.com", 
        "password" : "oKEuEU4FnlO4Efs", 
        "friends" : [], 
        "thoughts" : [] ,
        "stats": {"currentCh": 0}
    },
    { 
        "username" : "Alta.Kemmer20", 
        "email" : "Alta.Kemmer20.Gibson@hotmail.com", 
        "password" : "q4PGoZonm_KnlU7", 
        "thoughts" : [] ,
        "stats": {"currentCh": 0}
    },
    { 
        "username" : "Vladimir_Block", 
        "email" : "Vladimir_Block_Feil41@hotmail.com", 
        "password" : "q9AgUcyAQPmK5jJ", 
        "friends" : [] ,
        "stats": {"currentCh": 0}
    },
    { 
        "username" : "Mona_Hilll", 
        "email" : "Mona_Hilll_Zemlak@hotmail.com", 
        "password" : "GkOySb7J56E0Hpz", 
        "friends" : [], 
        "thoughts" : [] ,
        "stats": {"currentCh": 0}
    },
    { 
        "username" : "Alice_Simonis", 
        "email" : "Alice_Simonis8@gmail.com", 
        "password" : "ElVXqVGn9Tm_L38", 
        "friends" : [], 
        "thoughts" : [] ,
        "stats": {"currentCh": 0}
    },
    { 
        "username" : "Ayana.Bogisich", 
        "email" : "Ayana.Bogisich.Stoltenberg@yahoo.com", 
        "password" : "IjiJJXVWzlfLwA9", 
        "thoughts" : [] ,
        "stats": {"currentCh": 0}
    },
    { 
        "username" : "Annabelle79", 
        "email" : "Annabelle7973@hotmail.com", 
        "password" : "vhk6h6KQEJVC_kQ", 
        "thoughts" : [] ,
        "stats": {"currentCh": 0}
    },
    { 
        "username" : "Tyree17", 
        "email" : "Tyree17_Tillman@yahoo.com", 
        "password" : "TLhhBXjOVGKWP43", 
        "friends" : [] ,
        "stats": {"currentCh": 0}
    },
    { 
        "username" : "Eldridge42", 
        "email" : "Eldridge4262@yahoo.com", 
        "password" : "dcWBuw3ugFODuNy", 
        "friends" : [], 
        "thoughts" : [] ,
        "stats": {"currentCh": 0}
    }
]